card_shoe/__init__.py
card_shoe/card_shoe.py
card_shoe-0.0.4.dist-info/licenses/LICENSE
card_shoe-0.0.4.dist-info/METADATA
card_shoe-0.0.4.dist-info/WHEEL
card_shoe-0.0.4.dist-info/top_level.txt
card_shoe-0.0.4.dist-info/RECORD
