Metadata-Version: 2.4
Name: card_shoe
Version: 0.0.4
Summary: A Python card shoe library for creating card shoes with multiple decks for blackjack and casino usage.
Author-email: Peter Dang <peterhdangg@gmail.com>
License-Expression: MIT
Project-URL: Homepage, https://github.com/peterdang1502/card_shoe_lib
Project-URL: Issues, https://github.com/peterdang1502/card_shoe_lib/issues
Classifier: Programming Language :: Python :: 3
Classifier: Operating System :: OS Independent
Requires-Python: >=3.9
License-File: LICENSE
Requires-Dist: standard_playing_card
Dynamic: license-file
